Workbook

Sheet Merged_Annual_Data
A1: South Africa — Merged Annual Macroeconomic Series for M&A Threshold Benchmarking (1999–2026)
A2: CPI & GDP: Stats SA | Market Capitalisation: SARB | JSE All Share Index: JSE | See "Notes & Sources" tab for methodology, citations, and 2025/2026 partial-year treatment. Full monthly detail behind every series is in its own "_Monthly" tab.
A4: Year | B4: CPI Index (Dec 2024=100) | C4: CPI YoY % | D4: Nominal GDP (R million) | E4: Real GDP (R million, 2015 prices) | F4: GDP Deflator (Index, 2015=100) | G4: GDP Deflator YoY % | H4: GNP / GNI (R million) | I4: Market Capitalisation (R million) | J4: JSE All Share Index (ALSI, Annual Avg)
A5: 1999 | B5: =CPI_Annual!B4 -> 26.166667 | C5: =CPI_Annual!C4 -> 5.275 | D5: =GDP_Annual_Raw!B4 -> 925690.4 | E5: =GDP_Annual_Raw!C4 -> 2712790.6 | F5: =IFERROR(D5/E5*100,"") -> 34.123179 | H5: n/a | I5: =MarketCap_Annual!B4 -> 1616207 | J5: n/a
A6: 2000 | B6: =CPI_Annual!B5 -> 27.583333 | C6: =CPI_Annual!C5 -> 5.325 | D6: =GDP_Annual_Raw!B5 -> 1053138 | E6: =GDP_Annual_Raw!C5 -> 2826727.8 | F6: =IFERROR(D6/E6*100,"") -> 37.256435 | G6: =IFERROR((F6/F5-1)*100,"") -> 9.1821911 | H6: n/a | I6: =MarketCap_Annual!B5 -> 1551489 | J6: n/a
A7: 2001 | B7: =CPI_Annual!B6 -> 29.15 | C7: =CPI_Annual!C6 -> 5.725 | D7: =GDP_Annual_Raw!B6 -> 1165940.6 | E7: =GDP_Annual_Raw!C6 -> 2903049.5 | F7: =IFERROR(D7/E7*100,"") -> 40.162615 | G7: =IFERROR((F7/F6-1)*100,"") -> 7.8004791 | H7: n/a | I7: =MarketCap_Annual!B6 -> 1770682 | J7: n/a
A8: 2002 | B8: =CPI_Annual!B7 -> 31.816667 | C8: =CPI_Annual!C7 -> 9.15 | D8: =GDP_Annual_Raw!B7 -> 1360679.3 | E8: =GDP_Annual_Raw!C7 -> 3010473.1 | F8: =IFERROR(D8/E8*100,"") -> 45.198188 | G8: =IFERROR((F8/F7-1)*100,"") -> 12.537961 | H8: n/a | I8: =MarketCap_Annual!B7 -> 1584151 | J8: =ALSI_Annual!B7 -> 9608.0757
A9: 2003 | B9: =CPI_Annual!B8 -> 33.675 | C9: =CPI_Annual!C8 -> 5.9666667 | D9: =GDP_Annual_Raw!B8 -> 1490399 | E9: =GDP_Annual_Raw!C8 -> 3099254.3 | F9: =IFERROR(D9/E9*100,"") -> 48.088955 | G9: =IFERROR((F9/F8-1)*100,"") -> 6.3957575 | H9: n/a | I9: =MarketCap_Annual!B8 -> 1787194 | J9: =ALSI_Annual!B8 -> 8845.9075
A10: 2004 | B10: =CPI_Annual!B9 -> 34.15 | C10: =CPI_Annual!C9 -> 1.3916667 | D10: =GDP_Annual_Raw!B9 -> 1652434.1 | E10: =GDP_Annual_Raw!C9 -> 3240411.7 | F10: =IFERROR(D10/E10*100,"") -> 50.994573 | G10: =IFERROR((F10/F9-1)*100,"") -> 6.0421731 | H10: n/a | I10: =MarketCap_Annual!B9 -> 2566352 | J10: =ALSI_Annual!B9 -> 11114.682
A11: 2005 | B11: =CPI_Annual!B10 -> 35.275 | C11: =CPI_Annual!C10 -> 3.4 | D11: =GDP_Annual_Raw!B10 -> 1837001.4 | E11: =GDP_Annual_Raw!C10 -> 3411409.9 | F11: =IFERROR(D11/E11*100,"") -> 53.848744 | G11: =IFERROR((F11/F10-1)*100,"") -> 5.5970109 | H11: n/a | I11: =MarketCap_Annual!B10 -> 3586112 | J11: =ALSI_Annual!B10 -> 14900.743
A12: 2006 | B12: =CPI_Annual!B11 -> 36.916667 | C12: =CPI_Annual!C11 -> 4.6416667 | D12: =GDP_Annual_Raw!B11 -> 2057593.9 | E12: =GDP_Annual_Raw!C11 -> 3602578.7 | F12: =IFERROR(D12/E12*100,"") -> 57.114475 | G12: =IFERROR((F12/F11-1)*100,"") -> 6.0646358 | H12: n/a | I12: =MarketCap_Annual!B11 -> 5041515 | J12: =ALSI_Annual!B11 -> 21628.196
A13: 2007 | B13: =CPI_Annual!B12 -> 39.558333 | C13: =CPI_Annual!C12 -> 7.075 | D13: =GDP_Annual_Raw!B12 -> 2346649.9 | E13: =GDP_Annual_Raw!C12 -> 3795694 | F13: =IFERROR(D13/E13*100,"") -> 61.824001 | G13: =IFERROR((F13/F12-1)*100,"") -> 8.2457668 | H13: n/a | I13: =MarketCap_Annual!B12 -> 5696829 | J13: =ALSI_Annual!B12 -> 28452.39
A14: 2008 | B14: =CPI_Annual!B13 -> 44.133333 | C14: =CPI_Annual!C13 -> 11.525 | D14: =GDP_Annual_Raw!B13 -> 2611630.8 | E14: =GDP_Annual_Raw!C13 -> 3916816.2 | F14: =IFERROR(D14/E14*100,"") -> 66.67739 | G14: =IFERROR((F14/F13-1)*100,"") -> 7.8503308 | H14: n/a | I14: =MarketCap_Annual!B13 -> 4541938 | J14: =ALSI_Annual!B13 -> 26962.057
A15: 2009 | B15: =CPI_Annual!B14 -> 47.016667 | C15: =CPI_Annual!C14 -> 7.1416667 | D15: =GDP_Annual_Raw!B14 -> 2794228.4 | E15: =GDP_Annual_Raw!C14 -> 3856572.1 | F15: =IFERROR(D15/E15*100,"") -> 72.45368 | G15: =IFERROR((F15/F14-1)*100,"") -> 8.6630418 | H15: n/a | I15: =MarketCap_Annual!B14 -> 5929063 | J15: =ALSI_Annual!B14 -> 23323.907
A16: 2010 | B16: =CPI_Annual!B15 -> 49.033333 | C16: =CPI_Annual!C15 -> 4.2833333 | D16: =GDP_Annual_Raw!B15 -> 3055613.2 | E16: =GDP_Annual_Raw!C15 -> 3973801.6 | F16: =IFERROR(D16/E16*100,"") -> 76.893955 | G16: =IFERROR((F16/F15-1)*100,"") -> 6.1284325 | H16: n/a | I16: =MarketCap_Annual!B15 -> 6698700 | J16: =ALSI_Annual!B15 -> 28509.114
A17: 2011 | B17: =CPI_Annual!B16 -> 51.475 | C17: =CPI_Annual!C16 -> 4.9833333 | D17: =GDP_Annual_Raw!B16 -> 3327047 | E17: =GDP_Annual_Raw!C16 -> 4099713.7 | F17: =IFERROR(D17/E17*100,"") -> 81.153155 | G17: =IFERROR((F17/F16-1)*100,"") -> 5.5390571 | H17: n/a | I17: =MarketCap_Annual!B16 -> 6908507 | J17: =ALSI_Annual!B16 -> 31847.999
A18: 2012 | B18: =CPI_Annual!B17 -> 54.391667 | C18: =CPI_Annual!C17 -> 5.6666667 | D18: =GDP_Annual_Raw!B17 -> 3566385 | E18: =GDP_Annual_Raw!C17 -> 4197952.4 | F18: =IFERROR(D18/E18*100,"") -> 84.955346 | G18: =IFERROR((F18/F17-1)*100,"") -> 4.685205 | H18: n/a | I18: =MarketCap_Annual!B17 -> 8383564 | J18: =ALSI_Annual!B17 -> 35262.342
A19: 2013 | B19: =CPI_Annual!B18 -> 57.516667 | C19: =CPI_Annual!C18 -> 5.7583333 | D19: =GDP_Annual_Raw!B18 -> 3868630.2 | E19: =GDP_Annual_Raw!C18 -> 4302291.2 | F19: =IFERROR(D19/E19*100,"") -> 89.920231 | G19: =IFERROR((F19/F18-1)*100,"") -> 5.8441113 | H19: n/a | I19: =MarketCap_Annual!B18 -> 10626244 | J19: =ALSI_Annual!B18 -> 42057.111
... A32: 2026 | B32: =CPI_Annual!B31 -> 105.81429 | C32: =CPI_Annual!C31 -> 3.9142857 | D32: =GDP_Annual_Raw!B31 -> 7780960.6 | E32: =GDP_Annual_Raw!C31 -> 4737866.3 | F32: =IFERROR(D32/E32*100,"") -> 164.22921 | G32: =IFERROR((F32/F31-1)*100,"") -> 1.3641158 | H32: n/a | I32: =MarketCap_Annual!B31 -> 24713587 | J32: =ALSI_Annual!B31 -> 116312.68
A34: Amber row/cell = partial-year or estimated figure. Grey "n/a" = series not available for that year. See "Notes & Sources" for method.
A35: GNP/GNI is not published in the supplied Stats SA GDP release — see "Notes & Sources" for why and how it could be sourced.
A36: Full monthly detail behind each column: CPI_Monthly, GDP_Quarterly (Stats SA does not publish monthly GDP), MarketCap_Monthly, ALSI_Monthly.

Sheet Notes & Sources
A1: South African M&A Threshold Benchmarking Dataset
A2: Merged annual macroeconomic series with full monthly/quarterly detail, 1999–2026
A4: Workbook structure
A5: Merged_Annual_Data | B5: Main deliverable — one row per year, 1999-2026, formula-linked to the "_Annual" / raw sheets below. Nothing here is hardcoded.
A6: CPI_Monthly / CPI_Annual | B6: Full monthly CPI index & YoY%, 1999-2026 (Jul); CPI_Annual averages it up by year.
A7: GDP_Quarterly / GDP_Annual_Raw | B7: Quarterly GDP (finest grain Stats SA publishes — there is no monthly GDP series) and the annual roll-up.
A8: MarketCap_Monthly / MarketCap_Annual | B8: Full monthly SARB market cap series and the annual roll-up.
A9: ALSI_Monthly / ALSI_Annual | B9: Full monthly JSE All Share Index series and the annual roll-up.
A11: Series included & sources
A12: CPI headline index (Dec 2024 = 100) & YoY % | B12: Stats SA — CPI History release, Table B1 (index) & Table B2 (YoY rates), as provided (CPIHistory.pdf). Full monthly detail 1999-2026 (Jul) is in CPI_Monthly.
A13: Nominal & Real GDP at market prices (R million) | B13: Stats SA — P0441 GDP Time Series, Q1 2026 release. Annual series (AN1000/AR1000) run 1999-2025; quarterly series (QNU1000/QRU1000) run through 2026Q1 and are in GDP_Quarterly. No monthly GDP exists — quarterly is the finest granularity Stats SA publishes.
A14: GDP Deflator (index, 2015 = 100) | B14: Calculated, not separately published: Nominal GDP ÷ Real GDP × 100.
A15: GNP / GNI | B15: NOT AVAILABLE in the supplied Stats SA GDP release (P0441 covers domestic production only, no net primary income from abroad). Left as "n/a". Could be sourced from SARB Quarterly Bulletin KBP series if needed.
A16: Stock market capitalisation, JSE all exchanges (R million) | B16: SARB — series KBP2170J (annual, year-end) for 1999-2024, and KBP2170M (monthly, month-end) for the rest / for the monthly detail sheet. Full monthly series 1999-2026 is in MarketCap_Monthly.
A17: JSE All Share Index (ALSI, J203 Value) | B17: JSE — monthly closing index values, as supplied (Monthly_ALSI_Values_JSE.xlsx). History in the supplied file starts June 2002 — no data for 1999-2001, and 2002 is a partial year (Jun-Dec only). Full monthly detail (including Capped SWIX / J303, dividend yield, earnings yield columns) is in ALSI_Monthly; only the J203 Alsi Value (price index level) is carried into the main merged sheet, since it isolates price moves from the market-cap series, which reflects both price AND the number/size of listed shares.
A19: 2025 / 2026 (and 2002) partial-year calculation method
A20: CPI 2026 | B20: Average of the 7 published monthly index values (Jan-Jul 2026) and of the 7 published monthly YoY rates.
A21: Market cap 2025 | B21: December 2025 month-end value taken directly (matches how the annual series is defined for every other year).
A22: Market cap 2026 | B22: Average of the 5 published monthly month-end values (Jan-May 2026) — the year is incomplete.
A23: Nominal & Real GDP 2026 | B23: Trailing four-quarter sum (2025Q2+2025Q3+2025Q4+2026Q1) of quarterly actuals. NOT an official Stats SA annual figure.
A24: ALSI 2002 | B24: Average of the 7 published monthly values (Jun-Dec 2002) — no data before June 2002.
A25: ALSI 2026 | B25: Average of the 7 published monthly values (Jan-Jul 2026).
A27: M&A threshold benchmarking — how each series fits South Africa's asset/turnover test
A28: Nominal GDP | B28: Turnover thresholds are nominal Rand figures on an income statement — nominal GDP is the natural macro proxy for how aggregate firm turnover scales over time.
A29: CPI vs GDP Deflator | B29: Both are candidate indexation benchmarks. GDP deflator prices the whole economy's output and may track firm turnover/assets more closely than CPI, which is a consumer basket. Worth comparing both.
A30: Market capitalisation | B30: A genuine proxy for the asset-value side of the threshold, but covers listed firms only — most merger notifications involve unlisted firms, so treat as directional, not primary.
A31: JSE All Share Index | B31: Isolates price/valuation moves specifically (unlike market cap, which also moves with listings/delistings and share issuance) — useful to separate "the market grew because prices rose" from "the market grew because more/bigger firms listed."
A32: Producer Price Index (PPI) — not yet in this workbook | B32: Discussed separately: the "Metals, machinery, equipment and computing equipment" sub-index of Stats SA's Final Manufactured Goods PPI (Table 1) is the closest real published proxy for machinery/capital-asset price inflation, arguably better suited to an asset threshold than CPI. Can be added on request.
A34: Colour legend
A35: Blue text | B35: Hardcoded source figure, copied directly from the cited release.
A36: Black text | B36: Formula calculated from other cells in this workbook.
A37: Amber fill | B37: Partial-year / non-official estimate.
A38: Grey "n/a" | B38: Series not available for that year (no data exists / was published).

Sheet CPI_Annual
A1: CPI headline, annual — average of CPI_Monthly. 1999-2025 = full-year average; 2026 = partial year (Jan-Jul only, published so far)
A3: Year | B3: CPI Index (Annual Average) | C3: CPI YoY % (Annual Average) | D3: Note
A4: 1999 | B4: =AVERAGE(CPI_Monthly!C4:C15) -> 26.166667 | C4: =AVERAGE(CPI_Monthly!D4:D15) -> 5.275
A5: 2000 | B5: =AVERAGE(CPI_Monthly!C16:C27) -> 27.583333 | C5: =AVERAGE(CPI_Monthly!D16:D27) -> 5.325
A6: 2001 | B6: =AVERAGE(CPI_Monthly!C28:C39) -> 29.15 | C6: =AVERAGE(CPI_Monthly!D28:D39) -> 5.725
A7: 2002 | B7: =AVERAGE(CPI_Monthly!C40:C51) -> 31.816667 | C7: =AVERAGE(CPI_Monthly!D40:D51) -> 9.15
A8: 2003 | B8: =AVERAGE(CPI_Monthly!C52:C63) -> 33.675 | C8: =AVERAGE(CPI_Monthly!D52:D63) -> 5.9666667
A9: 2004 | B9: =AVERAGE(CPI_Monthly!C64:C75) -> 34.15 | C9: =AVERAGE(CPI_Monthly!D64:D75) -> 1.3916667
A10: 2005 | B10: =AVERAGE(CPI_Monthly!C76:C87) -> 35.275 | C10: =AVERAGE(CPI_Monthly!D76:D87) -> 3.4
A11: 2006 | B11: =AVERAGE(CPI_Monthly!C88:C99) -> 36.916667 | C11: =AVERAGE(CPI_Monthly!D88:D99) -> 4.6416667
A12: 2007 | B12: =AVERAGE(CPI_Monthly!C100:C111) -> 39.558333 | C12: =AVERAGE(CPI_Monthly!D100:D111) -> 7.075
A13: 2008 | B13: =AVERAGE(CPI_Monthly!C112:C123) -> 44.133333 | C13: =AVERAGE(CPI_Monthly!D112:D123) -> 11.525
A14: 2009 | B14: =AVERAGE(CPI_Monthly!C124:C135) -> 47.016667 | C14: =AVERAGE(CPI_Monthly!D124:D135) -> 7.1416667
A15: 2010 | B15: =AVERAGE(CPI_Monthly!C136:C147) -> 49.033333 | C15: =AVERAGE(CPI_Monthly!D136:D147) -> 4.2833333
A16: 2011 | B16: =AVERAGE(CPI_Monthly!C148:C159) -> 51.475 | C16: =AVERAGE(CPI_Monthly!D148:D159) -> 4.9833333
A17: 2012 | B17: =AVERAGE(CPI_Monthly!C160:C171) -> 54.391667 | C17: =AVERAGE(CPI_Monthly!D160:D171) -> 5.6666667
A18: 2013 | B18: =AVERAGE(CPI_Monthly!C172:C183) -> 57.516667 | C18: =AVERAGE(CPI_Monthly!D172:D183) -> 5.7583333
A19: 2014 | B19: =AVERAGE(CPI_Monthly!C184:C195) -> 61.016667 | C19: =AVERAGE(CPI_Monthly!D184:D195) -> 6.05
A20: 2015 | B20: =AVERAGE(CPI_Monthly!C196:C207) -> 63.825 | C20: =AVERAGE(CPI_Monthly!D196:D207) -> 4.5833333
A21: 2016 | B21: =AVERAGE(CPI_Monthly!C208:C219) -> 67.833333 | C21: =AVERAGE(CPI_Monthly!D208:D219) -> 6.325
A22: 2017 | B22: =AVERAGE(CPI_Monthly!C220:C231) -> 71.441667 | C22: =AVERAGE(CPI_Monthly!D220:D231) -> 5.2833333
A23: 2018 | B23: =AVERAGE(CPI_Monthly!C232:C243) -> 74.725 | C23: =AVERAGE(CPI_Monthly!D232:D243) -> 4.6166667
A24: 2019 | B24: =AVERAGE(CPI_Monthly!C244:C255) -> 77.8 | C24: =AVERAGE(CPI_Monthly!D244:D255) -> 4.1416667
A25: 2020 | B25: =AVERAGE(CPI_Monthly!C256:C267) -> 80.358333 | C25: =AVERAGE(CPI_Monthly!D256:D267) -> 3.2833333
A26: 2021 | B26: =AVERAGE(CPI_Monthly!C268:C279) -> 84.016667 | C26: =AVERAGE(CPI_Monthly!D268:D279) -> 4.5583333
A27: 2022 | B27: =AVERAGE(CPI_Monthly!C280:C291) -> 89.783333 | C27: =AVERAGE(CPI_Monthly!D280:D291) -> 6.85
A28: 2023 | B28: =AVERAGE(CPI_Monthly!C292:C303) -> 95.083333 | C28: =AVERAGE(CPI_Monthly!D292:D303) -> 5.9083333
A29: 2024 | B29: =AVERAGE(CPI_Monthly!C304:C315) -> 99.291667 | C29: =AVERAGE(CPI_Monthly!D304:D315) -> 4.4333333
A30: 2025 | B30: =AVERAGE(CPI_Monthly!C316:C327) -> 102.49167 | C30: =AVERAGE(CPI_Monthly!D316:D327) -> 3.2166667
A31: 2026 | B31: =AVERAGE(CPI_Monthly!C328:C334) -> 105.81429 | C31: =AVERAGE(CPI_Monthly!D328:D334) -> 3.9142857 | D31: Partial year (Jan-Jul only)

Sheet CPI_Monthly
A1: CPI headline, monthly — Stats SA, CPI History release (Table B1 index, Table B2 YoY %)
A3: Year | B3: Month | C3: CPI Index (Dec 2024=100) | D3: CPI YoY %
A4: 1999 | B4: Jan | C4: 26 | D4: 8.9
A5: 1999 | B5: Feb | C5: 26 | D5: 8.6
A6: 1999 | B6: Mar | C6: 26 | D6: 7.9
A7: 1999 | B7: Apr | C7: 26.1 | D7: 7.7
A8: 1999 | B8: May | C8: 26.1 | D8: 7.1
A9: 1999 | B9: Jun | C9: 26.2 | D9: 7.3
A10: 1999 | B10: Jul | C10: 26.2 | D10: 4.9
A11: 1999 | B11: Aug | C11: 26.1 | D11: 3.2
A12: 1999 | B12: Sep | C12: 26.2 | D12: 1.9
A13: 1999 | B13: Oct | C13: 26.3 | D13: 1.7
A14: 1999 | B14: Nov | C14: 26.4 | D14: 1.9
A15: 1999 | B15: Dec | C15: 26.4 | D15: 2.2
... A334: 2026 | B334: Jul | C334: 107.7 | D334: 4.3

Sheet GDP_Annual_Raw
A1: GDP at market prices, annual — Stats SA P0441 Q1 2026, "Annual" sheet (AN1000 / AR1000); 2026 estimated from trailing 4 quarters, see GDP_Quarterly
A3: Year | B3: Nominal GDP (R million, current prices) | C3: Real GDP (R million, 2015 prices) | D3: Note
A4: 1999 | B4: 925690.4 | C4: 2712790.6
A5: 2000 | B5: 1053138 | C5: 2826727.8
A6: 2001 | B6: 1165940.6 | C6: 2903049.5
A7: 2002 | B7: 1360679.3 | C7: 3010473.1
A8: 2003 | B8: 1490399 | C8: 3099254.3
A9: 2004 | B9: 1652434.1 | C9: 3240411.7
A10: 2005 | B10: 1837001.4 | C10: 3411409.9
A11: 2006 | B11: 2057593.9 | C11: 3602578.7
A12: 2007 | B12: 2346649.9 | C12: 3795694
A13: 2008 | B13: 2611630.8 | C13: 3916816.2
A14: 2009 | B14: 2794228.4 | C14: 3856572.1
A15: 2010 | B15: 3055613.2 | C15: 3973801.6
... A30: 2025 | B30: 7641793.2 | C30: 4716600.6
A31: 2026 | B31: =SUM(GDP_Quarterly!C109,GDP_Quarterly!C110,GDP_Quarterly!C111,GDP_Quarterly!C112) -> 7780960.6 | C31: =SUM(GDP_Quarterly!D109,GDP_Quarterly!D110,GDP_Quarterly!D111,GDP_Quarterly!D112) -> 4737866.3 | D31: Trailing 4-quarter sum (2025Q2-2026Q1), NOT an official Stats SA annual figure

Sheet GDP_Quarterly
A1: GDP at market prices, quarterly (actual, not seasonally adjusted) — Stats SA P0441 Q1 2026, "Quarterly" sheet (QNU1000 / QRU1000)
A2: Note: Stats SA does not publish a monthly GDP series — quarterly is the finest granularity available. Shown here as the monthly-equivalent detail sheet for GDP.
A4: Year | B4: Quarter | C4: Nominal GDP (R million) | D4: Real GDP (R million, 2015 prices)
A5: 1999 | B5: Q1 | C5: 217376.3 | D5: 650460.8
A6: 1999 | B6: Q2 | C6: 225691.7 | D6: 677457.9
A7: 1999 | B7: Q3 | C7: 238959.5 | D7: 687695.8
A8: 1999 | B8: Q4 | C8: 243662.9 | D8: 697176.1
A9: 2000 | B9: Q1 | C9: 244300 | D9: 673853.8
A10: 2000 | B10: Q2 | C10: 257523.3 | D10: 700641.1
A11: 2000 | B11: Q3 | C11: 273459.8 | D11: 723788.5
A12: 2000 | B12: Q4 | C12: 277854.9 | D12: 728444.3
A13: 2001 | B13: Q1 | C13: 278789.9 | D13: 699015
A14: 2001 | B14: Q2 | C14: 287788.9 | D14: 726480.4
A15: 2001 | B15: Q3 | C15: 295577.6 | D15: 734714.4
A16: 2001 | B16: Q4 | C16: 303784.2 | D16: 742839.7
... A112: 2026 | B112: Q1 | C112: 1938242.7 | D112: 1167288.2

Sheet MarketCap_Annual
A1: JSE market capitalisation, annual — SARB. 1999-2025 = December (year-end) month-end value; 2026 = average of Jan-May 2026 (partial year, year-end not yet available)
A3: Year | B3: Market Capitalisation (R million) | C3: Basis | D3: Note
A4: 1999 | B4: =MarketCap_Monthly!C15 -> 1616207 | C4: Year-end (December)
A5: 2000 | B5: =MarketCap_Monthly!C27 -> 1551489 | C5: Year-end (December)
A6: 2001 | B6: =MarketCap_Monthly!C39 -> 1770682 | C6: Year-end (December)
A7: 2002 | B7: =MarketCap_Monthly!C51 -> 1584151 | C7: Year-end (December)
A8: 2003 | B8: =MarketCap_Monthly!C63 -> 1787194 | C8: Year-end (December)
A9: 2004 | B9: =MarketCap_Monthly!C75 -> 2566352 | C9: Year-end (December)
A10: 2005 | B10: =MarketCap_Monthly!C87 -> 3586112 | C10: Year-end (December)
A11: 2006 | B11: =MarketCap_Monthly!C99 -> 5041515 | C11: Year-end (December)
A12: 2007 | B12: =MarketCap_Monthly!C111 -> 5696829 | C12: Year-end (December)
A13: 2008 | B13: =MarketCap_Monthly!C123 -> 4541938 | C13: Year-end (December)
A14: 2009 | B14: =MarketCap_Monthly!C135 -> 5929063 | C14: Year-end (December)
A15: 2010 | B15: =MarketCap_Monthly!C147 -> 6698700 | C15: Year-end (December)
A16: 2011 | B16: =MarketCap_Monthly!C159 -> 6908507 | C16: Year-end (December)
A17: 2012 | B17: =MarketCap_Monthly!C171 -> 8383564 | C17: Year-end (December)
A18: 2013 | B18: =MarketCap_Monthly!C183 -> 10626244 | C18: Year-end (December)
A19: 2014 | B19: =MarketCap_Monthly!C195 -> 11505020 | C19: Year-end (December)
A20: 2015 | B20: =MarketCap_Monthly!C207 -> 11727560 | C20: Year-end (December)
A21: 2016 | B21: =MarketCap_Monthly!C219 -> 13580619 | C21: Year-end (December)
A22: 2017 | B22: =MarketCap_Monthly!C231 -> 15467873 | C22: Year-end (December)
A23: 2018 | B23: =MarketCap_Monthly!C243 -> 12701949 | C23: Year-end (December)
A24: 2019 | B24: =MarketCap_Monthly!C255 -> 17459094 | C24: Year-end (December)
A25: 2020 | B25: =MarketCap_Monthly!C267 -> 17874362 | C25: Year-end (December)
A26: 2021 | B26: =MarketCap_Monthly!C279 -> 20520438 | C26: Year-end (December)
A27: 2022 | B27: =MarketCap_Monthly!C291 -> 21356714 | C27: Year-end (December)
A28: 2023 | B28: =MarketCap_Monthly!C303 -> 19023628 | C28: Year-end (December)
A29: 2024 | B29: =MarketCap_Monthly!C315 -> 19239200 | C29: Year-end (December)
A30: 2025 | B30: =MarketCap_Monthly!C327 -> 24187552 | C30: Year-end (December)
A31: 2026 | B31: =AVERAGE(MarketCap_Monthly!C328:C332) -> 24713587 | C31: Average of Jan-May (partial year) | D31: Partial year, indicative only

Sheet MarketCap_Monthly
A1: JSE all-exchanges market capitalisation, monthly — SARB, series KBP2170M (R million, month-end)
A3: Year | B3: Month | C3: Market Capitalisation (R million)
A4: 1999 | B4: Jan | C4: 1067747
A5: 1999 | B5: Feb | C5: 1090936
A6: 1999 | B6: Mar | C6: 1188083
A7: 1999 | B7: Apr | C7: 1318940
A8: 1999 | B8: May | C8: 1208849
A9: 1999 | B9: Jun | C9: 1317575
A10: 1999 | B10: Jul | C10: 1366622
A11: 1999 | B11: Aug | C11: 1336666
A12: 1999 | B12: Sep | C12: 1304210
A13: 1999 | B13: Oct | C13: 1364059
A14: 1999 | B14: Nov | C14: 1442156
A15: 1999 | B15: Dec | C15: 1616207
... A332: 2026 | B332: May | C332: 24970792

Sheet ALSI_Annual
A1: JSE All Share Index, annual average of month-end closes — JSE. No data before June 2002; 2002 and 2026 are partial years.
A3: Year | B3: ALSI Index (Annual Average, J203 Value) | C3: Basis | D3: Note
A4: 1999 | B4: n/a | C4: No data | D4: JSE ALSI history in the supplied file starts June 2002
A5: 2000 | B5: n/a | C5: No data | D5: JSE ALSI history in the supplied file starts June 2002
A6: 2001 | B6: n/a | C6: No data | D6: JSE ALSI history in the supplied file starts June 2002
A7: 2002 | B7: =AVERAGE(ALSI_Monthly!B4:B10) -> 9608.0757 | C7: Average of Jun-Dec (partial year) | D7: Partial year
A8: 2003 | B8: =AVERAGE(ALSI_Monthly!B11:B22) -> 8845.9075 | C8: Full-year average
A9: 2004 | B9: =AVERAGE(ALSI_Monthly!B23:B34) -> 11114.682 | C9: Full-year average
A10: 2005 | B10: =AVERAGE(ALSI_Monthly!B35:B46) -> 14900.743 | C10: Full-year average
A11: 2006 | B11: =AVERAGE(ALSI_Monthly!B47:B58) -> 21628.196 | C11: Full-year average
A12: 2007 | B12: =AVERAGE(ALSI_Monthly!B59:B70) -> 28452.39 | C12: Full-year average
A13: 2008 | B13: =AVERAGE(ALSI_Monthly!B71:B82) -> 26962.057 | C13: Full-year average
A14: 2009 | B14: =AVERAGE(ALSI_Monthly!B83:B94) -> 23323.907 | C14: Full-year average
A15: 2010 | B15: =AVERAGE(ALSI_Monthly!B95:B106) -> 28509.114 | C15: Full-year average
A16: 2011 | B16: =AVERAGE(ALSI_Monthly!B107:B118) -> 31847.999 | C16: Full-year average
A17: 2012 | B17: =AVERAGE(ALSI_Monthly!B119:B130) -> 35262.342 | C17: Full-year average
A18: 2013 | B18: =AVERAGE(ALSI_Monthly!B131:B142) -> 42057.111 | C18: Full-year average
A19: 2014 | B19: =AVERAGE(ALSI_Monthly!B143:B154) -> 49231.354 | C19: Full-year average
A20: 2015 | B20: =AVERAGE(ALSI_Monthly!B155:B166) -> 51960.081 | C20: Full-year average
A21: 2016 | B21: =AVERAGE(ALSI_Monthly!B167:B178) -> 51568.447 | C21: Full-year average
A22: 2017 | B22: =AVERAGE(ALSI_Monthly!B179:B190) -> 55045.681 | C22: Full-year average
A23: 2018 | B23: =AVERAGE(ALSI_Monthly!B191:B202) -> 56075.818 | C23: Full-year average
A24: 2019 | B24: =AVERAGE(ALSI_Monthly!B203:B214) -> 56227.616 | C24: Full-year average
A25: 2020 | B25: =AVERAGE(ALSI_Monthly!B215:B226) -> 53369.854 | C25: Full-year average
A26: 2021 | B26: =AVERAGE(ALSI_Monthly!B227:B238) -> 67381.233 | C26: Full-year average
A27: 2022 | B27: =AVERAGE(ALSI_Monthly!B239:B250) -> 70926.199 | C27: Full-year average
A28: 2023 | B28: =AVERAGE(ALSI_Monthly!B251:B262) -> 75918.314 | C28: Full-year average
A29: 2024 | B29: =AVERAGE(ALSI_Monthly!B263:B274) -> 80113.578 | C29: Full-year average
A30: 2025 | B30: =AVERAGE(ALSI_Monthly!B275:B286) -> 98934.225 | C30: Full-year average
A31: 2026 | B31: =AVERAGE(ALSI_Monthly!B287:B293) -> 116312.68 | C31: Average of Jan-Jul (partial year) | D31: Partial year

Sheet ALSI_Monthly
A1: JSE All Share Index (ALSI), monthly closing values — JSE
A3: Date | B3: J203 - Alsi Value | C3: J203 - Alsi TRI | D3: J203 - Alsi DY (%) | E3: J203 - Alsi EY (%) | F3: J303 - Capi Value | G3: J303 - Capi TRI | H3: J303 - Capi DY (%) | I3: J303 - Capi EY (%)
A4: 2002-06-28 | B4: 10657.73 | C4: 958.17 | D4: 2.94 | F4: 5094.36 | G4: 5173.71 | H4: 2.94
A5: 2002-07-31 | B5: 9239.02 | C5: 832.29 | D5: 3.35 | F5: 4482.48 | G5: 4562.34 | H5: 3.3
A6: 2002-08-30 | B6: 9677.26 | C6: 874.78 | D6: 3.35 | F6: 4693.64 | G6: 4795.15 | H6: 3.31
A7: 2002-09-30 | B7: 9465.33 | C7: 861.29 | D7: 3.53 | F7: 4589.37 | G7: 4717.15 | H7: 3.52
A8: 2002-10-31 | B8: 9376.23 | C8: 856.12 | D8: 3.53 | F8: 4548.59 | G8: 4692.24 | H8: 3.52
A9: 2002-11-29 | B9: 9563.74 | C9: 874.55 | D9: 3.38 | F9: 4647.43 | G9: 4801.79 | H9: 3.37
A10: 2002-12-31 | B10: 9277.22 | C10: 849.66 | D10: 3.43 | F10: 4506.65 | G10: 4663.87 | H10: 3.44
A11: 2003-01-31 | B11: 8798.35 | C11: 807.44 | D11: 3.69 | F11: 4277.04 | G11: 4435.76 | H11: 3.7
A12: 2003-02-28 | B12: 8402.09 | C12: 772.67 | D12: 3.81 | F12: 4076.42 | G12: 4236.99 | H12: 3.83
A13: 2003-03-31 | B13: 7679.88 | C13: 711.38 | D13: 4.15 | F13: 3713.19 | G13: 3883.45 | H13: 4.2
A14: 2003-04-30 | B14: 7510.4 | C14: 699.56 | D14: 4.22 | F14: 3644.75 | G14: 3834.71 | H14: 4.27
A15: 2003-05-30 | B15: 8564.33 | C15: 797.96 | D15: 3.85 | F15: 4143.5 | G15: 4360.83 | H15: 3.89
... A58: 2006-12-29 | B58: 24915.2 | C58: 2573 | D58: 2.22 | F58: 12244.89 | G58: 14303 | H58: 2.25
A59: 2007-01-31 | B59: 25447.73 | C59: 2630.44 | D59: 2.2 | E59: 5.69 | F59: 12533.55 | G59: 14654.66 | H59: 2.22 | I59: 5.72
A60: 2007-02-28 | B60: 25795.99 | C60: 2669.93 | D60: 2.21 | E60: 6.37 | F60: 12698.13 | G60: 14867.49 | H60: 2.23 | I60: 6.31
A61: 2007-03-30 | B61: 27267.24 | C61: 2840.11 | D61: 2.28 | E61: 6.42 | F61: 13379.56 | G61: 15756.76 | H61: 2.31 | I61: 6.38
A62: 2007-04-30 | B62: 28170.6 | C62: 2938.91 | D62: 2.24 | E62: 6.23 | F62: 13866.94 | G62: 16358.66 | H62: 2.26 | I62: 6.18
A63: 2007-05-31 | B63: 28627.79 | C63: 2990.31 | D63: 2.23 | E63: 6.31 | F63: 13996.48 | G63: 16533.29 | H63: 2.27 | I63: 6.3
A64: 2007-06-29 | B64: 28337.22 | C64: 2961.9 | D64: 2.26 | E64: 6.4 | F64: 13863.01 | G64: 16387.23 | H64: 2.32 | I64: 6.38
A65: 2007-07-31 | B65: 28561.81 | C65: 2990.27 | D65: 2.3 | E65: 6.4 | F65: 13970.69 | G65: 16544.35 | H65: 2.35 | I65: 6.39
A66: 2007-08-31 | B66: 28660.35 | C66: 3010.38 | D66: 2.34 | E66: 6.86 | F66: 14029.62 | G66: 16665.3 | H66: 2.39 | I66: 6.76
A67: 2007-09-28 | B67: 29959.19 | C67: 3160.72 | D67: 2.36 | E67: 6.63 | F67: 14544.82 | G67: 17356.29 | H67: 2.45 | I67: 6.59
A68: 2007-10-31 | B68: 31334.99 | C68: 3312.24 | D68: 2.3 | E68: 6.33 | F68: 15297.36 | G68: 18293.56 | H68: 2.37 | I68: 6.26
A69: 2007-11-30 | B69: 30307.8 | C69: 3206.56 | D69: 2.39 | E69: 6.56 | F69: 14803.3 | G69: 17720.45 | H69: 2.47 | I69: 6.49
A70: 2007-12-31 | B70: 28957.97 | C70: 3066.87 | D70: 2.55 | E70: 6.89 | F70: 14201.82 | G70: 17019.47 | H70: 2.61 | I70: 6.8
... A293: 2026-07-31 | B293: 111493.1 | C293: 21496.313 | D293: 3.47 | E293: 7.48 | F293: 55805.681 | G293: 123747.8 | H293: 3.47 | I293: 7.48
